testofpy_package_mani/__init__.py
purposefully_malicious_mani-1.0.1.dist-info/LICENSE
purposefully_malicious_mani-1.0.1.dist-info/METADATA
purposefully_malicious_mani-1.0.1.dist-info/WHEEL
purposefully_malicious_mani-1.0.1.dist-info/top_level.txt
purposefully_malicious_mani-1.0.1.dist-info/RECORD
